setup.py
genai_pygame/__init__.py
genai_pygame/main.py
genai_pygame.egg-info/PKG-INFO
genai_pygame.egg-info/SOURCES.txt
genai_pygame.egg-info/dependency_links.txt
genai_pygame.egg-info/requires.txt
genai_pygame.egg-info/top_level.txt