Metadata-Version: 2.4
Name: genai_pygame
Version: 0.1.2
Summary: A helpful PyGame tool for intergrating Generative AI models into game projects.
Author: Alex Khon
Author-email: alexoverkode@hotmail.com
Requires-Dist: transformers
Dynamic: author
Dynamic: author-email
Dynamic: requires-dist
Dynamic: summary
